local_solar_watt/__init__.py
local_solar_watt/api.py
local_solar_watt/base/__init__.py
local_solar_watt/base/base_client.py
local_solar_watt/base/base_handler.py
local_solar_watt/clients/__init__.py
local_solar_watt/clients/mock_client.py
local_solar_watt/clients/rest_client.py
local_solar_watt/const/__init__.py
local_solar_watt/const/device.py
local_solar_watt/const/name_filter.py
local_solar_watt/const/tags_classic.py
local_solar_watt/const/tags_flex.py
local_solar_watt/const/units.py
local_solar_watt/handlers/__init__.py
local_solar_watt/handlers/classic.py
local_solar_watt/handlers/flex.py
local_solar_watt/openhab/__init__.py
local_solar_watt/openhab/ha_entity.py
local_solar_watt/openhab/items.py
localsolarwatt-0.8.2.dist-info/licenses/LICENSE.txt
localsolarwatt-0.8.2.dist-info/METADATA
localsolarwatt-0.8.2.dist-info/WHEEL
localsolarwatt-0.8.2.dist-info/top_level.txt
localsolarwatt-0.8.2.dist-info/RECORD
