Metadata-Version: 2.4
Name: LocalSolarWatt
Version: 0.8.2
Summary: python api wrapper for solar watt device api
Author: AlgorithmicEntropy
License-Expression: MIT
Project-URL: Homepage, https://github.com/AlgorithmicEntropy/SolarWattEnergyManagerAPI
Project-URL: Repository, https://github.com/AlgorithmicEntropy/SolarWattEnergyManagerAPI
Project-URL: Download, https://github.com/AlgorithmicEntropy/SolarWattEnergyManagerAPI/releases/latest
Keywords: IOT,Solar,Local
Classifier: Development Status :: 3 - Alpha
Classifier: Intended Audience :: Developers
Classifier: Topic :: Software Development :: Build Tools
Classifier: Programming Language :: Python :: 3
Classifier: Programming Language :: Python :: 3.13
Requires-Python: >=3.13
License-File: LICENSE.txt
Requires-Dist: requests==2.32.5
Dynamic: license-file
